airflow_config/__init__.py
airflow_config/dag.py
airflow_config/exceptions.py
airflow_config/utils.py
airflow_config/configuration/__init__.py
airflow_config/configuration/base.py
airflow_config/configuration/omegaconf_resolvers.py
airflow_config/configuration/reexports.py
airflow_config/configuration/hydra/__init__.py
airflow_config/configuration/hydra/conf.yaml
airflow_config/configuration/hydra/airflow_config/default_dag_args/default.yaml
airflow_config/configuration/hydra/airflow_config/default_task_args/default.yaml
airflow_config/configuration/hydra/hydra/hydra_logging/airflow_config/custom.yaml
airflow_config/configuration/hydra/hydra/job_logging/airflow_config/custom.yaml
airflow_config/tests/__init__.py
airflow_config/tests/airflow.cfg.jinja
airflow_config/tests/conftest.py
airflow_config/tests/test_dag.py
airflow_config/tests/test_ui.py
airflow_config/tests/setups/__init__.py
airflow_config/tests/setups/bad_nofile/test_no_file.py
airflow_config/tests/setups/bad_nofile/config/.gitkeep
airflow_config/tests/setups/basic/test_basic_empty.py
airflow_config/tests/setups/basic/test_change_globals.py
airflow_config/tests/setups/basic/test_complex.py
airflow_config/tests/setups/basic/test_options.py
airflow_config/tests/setups/basic/config/basic.yaml
airflow_config/tests/setups/basic/config/basic2.yaml
airflow_config/tests/setups/basic/config/complex.yaml
airflow_config/tests/setups/basic/config/options.yaml
airflow_config/tests/setups/basic/config/default_args/owner.yaml
airflow_config/tests/setups/basic/config/extensions/balancer.yaml
airflow_config/tests/setups/basic/config/extensions/libraries.yaml
airflow_config/tests/setups/basic/config/extensions/supervisor.yaml
airflow_config/tests/setups/envs/test_envs.py
airflow_config/tests/setups/envs/config/dev.yaml
airflow_config/tests/setups/envs/config/prod.yaml
airflow_config/tests/setups/factory/test_factory.py
airflow_config/tests/setups/factory/test_factory_render.py
airflow_config/tests/setups/factory/utils.py
airflow_config-1.11.0.dist-info/METADATA
airflow_config-1.11.0.dist-info/WHEEL
airflow_config-1.11.0.dist-info/entry_points.txt
airflow_config-1.11.0.dist-info/licenses/LICENSE
airflow_config-1.11.0.dist-info/RECORD
