Metadata-Version: 2.4
Name: airflow-config
Version: 1.11.0
Summary: Airflow utilities for configuration of many DAGs and DAG environments
Project-URL: Repository, https://github.com/airflow-laminar/airflow-config
Project-URL: Homepage, https://github.com/airflow-laminar/airflow-config
Author-email: the airflow-config authors <t.paine154@gmail.com>
License: Apache-2.0
License-File: LICENSE
Keywords: airflow,config,scheduler
Classifier: Development Status :: 4 - Beta
Classifier: Programming Language :: Python
Classifier: Programming Language :: Python :: 3
Classifier: Programming Language :: Python :: 3.9
Classifier: Programming Language :: Python :: 3.10
Classifier: Programming Language :: Python :: 3.11
Classifier: Programming Language :: Python :: 3.12
Classifier: Programming Language :: Python :: 3.13
Classifier: Programming Language :: Python :: 3.14
Classifier: Programming Language :: Python :: Implementation :: CPython
Classifier: Programming Language :: Python :: Implementation :: PyPy
Requires-Python: >=3.9
Requires-Dist: airflow-pydantic<1.6,>=1.5.4
Requires-Dist: colorlog
Requires-Dist: hydra-core
Requires-Dist: jinja2
Requires-Dist: omegaconf
Requires-Dist: pydantic>=2
Provides-Extra: airflow
Requires-Dist: apache-airflow-providers-ssh; extra == 'airflow'
Requires-Dist: apache-airflow-providers-standard; extra == 'airflow'
Requires-Dist: apache-airflow<3.1,>=2.9; extra == 'airflow'
Requires-Dist: paramiko<4; extra == 'airflow'
Provides-Extra: develop
Requires-Dist: airflow-balancer>=0.6.0; extra == 'develop'
Requires-Dist: airflow-common-operators; extra == 'develop'
Requires-Dist: airflow-priority>=1.5; extra == 'develop'
Requires-Dist: airflow-pydantic>=1.3; extra == 'develop'
Requires-Dist: airflow-supervisor>=1.7; extra == 'develop'
Requires-Dist: apache-airflow-providers-ssh; extra == 'develop'
Requires-Dist: apache-airflow-providers-standard; extra == 'develop'
Requires-Dist: apache-airflow<3.1,>=2.9; extra == 'develop'
Requires-Dist: build; extra == 'develop'
Requires-Dist: bump-my-version; extra == 'develop'
Requires-Dist: check-manifest; extra == 'develop'
Requires-Dist: codespell<2.5,>=2.4; extra == 'develop'
Requires-Dist: email-validator>=2; extra == 'develop'
Requires-Dist: fastapi; extra == 'develop'
Requires-Dist: flask; extra == 'develop'
Requires-Dist: flask-appbuilder; extra == 'develop'
Requires-Dist: hatch-js; extra == 'develop'
Requires-Dist: hatchling; extra == 'develop'
Requires-Dist: mdformat-tables>=1; extra == 'develop'
Requires-Dist: mdformat<0.8,>=0.7.22; extra == 'develop'
Requires-Dist: paramiko<4; extra == 'develop'
Requires-Dist: pytest; extra == 'develop'
Requires-Dist: pytest-cov; extra == 'develop'
Requires-Dist: ruff; extra == 'develop'
Requires-Dist: twine; extra == 'develop'
Requires-Dist: uvicorn; extra == 'develop'
Requires-Dist: wheel; extra == 'develop'
